adapt/__init__.py
adapt/client.py
adapt/connection.py
adapt/http.py
adapt/polyfill.py
adapt/py.typed
adapt/server.py
adapt/util.py
adapt/websocket.py
adapt/models/__init__.py
adapt/models/asset.py
adapt/models/bitflags.py
adapt/models/channel.py
adapt/models/enums.py
adapt/models/guild.py
adapt/models/member.py
adapt/models/message.py
adapt/models/object.py
adapt/models/ready.py
adapt/models/user.py
adapt/types/__init__.py
adapt/types/channel.py
adapt/types/guild.py
adapt/types/message.py
adapt/types/presence.py
adapt/types/role.py
adapt/types/user.py
adapt/types/ws.py
adapt.py-0.1.0a0.dist-info/LICENSE
adapt.py-0.1.0a0.dist-info/METADATA
adapt.py-0.1.0a0.dist-info/WHEEL
adapt.py-0.1.0a0.dist-info/top_level.txt
adapt.py-0.1.0a0.dist-info/RECORD
