Metadata-Version: 2.1
Name: adapt.py
Version: 0.1.0a0
Summary: Official wrapper around Adapt's API for Python.
Home-page: https://github.com/AdaptChat/adapt.py
Author: jay3332
License: MIT
Project-URL: Issue tracker, https://github.com/AdaptChat/adapt.py/issues/new
Project-URL: Documentation, https://adaptpy.readthedocs.io/en/latest/
Project-URL: Discord server, https://discord.gg/5BUFNBPG
Classifier: Development Status :: 4 - Beta
Classifier: License :: OSI Approved :: MIT License
Classifier: Intended Audience :: Developers
Classifier: Natural Language :: English
Classifier: Operating System :: OS Independent
Classifier: Programming Language :: Python :: 3.8
Classifier: Programming Language :: Python :: 3.9
Classifier: Programming Language :: Python :: 3.10
Classifier: Programming Language :: Python :: 3.11
Classifier: Topic :: Internet
Classifier: Topic :: Software Development :: Libraries
Classifier: Topic :: Software Development :: Libraries :: Python Modules
Classifier: Topic :: Utilities
Classifier: Typing :: Typed
Requires-Python: >=3.8.0
License-File: LICENSE
Requires-Dist: aiohttp (>=3.8.0)
Provides-Extra: docs
Requires-Dist: sphinx (>=4.1.1) ; extra == 'docs'
Requires-Dist: furo ; extra == 'docs'
Provides-Extra: performance
Requires-Dist: aiohttp[speedups] ; extra == 'performance'
Requires-Dist: msgpack ; extra == 'performance'
